lidarpy/__init__.py
lidarpy/cloud/__init__.py
lidarpy/cloud/cloud.py
lidarpy/data/__init__.py
lidarpy/data/read_binary.py
lidarpy/data/signal_operations.py
lidarpy/inversion/__init__.py
lidarpy/inversion/elastic_inversion.py
lidarpy/inversion/inelastic_inversion.py
lidarpy/inversion/transmittance.py
lidarpy/molecular/__init__.py
lidarpy/molecular/alpha_beta_mol.py
lidarpy/multiple_scattering/__init__.py
lidarpy/multiple_scattering/multiple_scaterring.py
lidarpy/utils/__init__.py
lidarpy/utils/constants.py
lidarpy/utils/functions.py
lidarpy/utils/raman_functions.py
lidarpy-0.0.9.dist-info/LICENSE
lidarpy-0.0.9.dist-info/METADATA
lidarpy-0.0.9.dist-info/WHEEL
lidarpy-0.0.9.dist-info/top_level.txt
lidarpy-0.0.9.dist-info/RECORD
