Metadata-Version: 2.1
Name: lidarpy
Version: 0.0.9
Summary: LIDARpy is a comprehensive Python library tailored for the analysis, manipulation, and interpretation of LIDAR data.
Author: Luan Cordeiro
Author-email: <luancordeiro@usp.br>
Keywords: python,lidar,clouds,data
Classifier: Development Status :: 3 - Alpha
Classifier: Intended Audience :: Science/Research
Classifier: Programming Language :: Python :: 3
Classifier: Operating System :: Unix
Classifier: Operating System :: MacOS :: MacOS X
Classifier: Operating System :: Microsoft :: Windows
License-File: LICENSE
Requires-Dist: numpy
Requires-Dist: xarray
Requires-Dist: scipy
Requires-Dist: datetime
